tikhub/__init__.py
tikhub/client.py
tikhub/sdk.py
tikhub/version.py
tikhub/api/__init__.py
tikhub/api/v1/__init__.py
tikhub/api/v1/endpoints/__init__.py
tikhub/api/v1/endpoints/bilibili/__init__.py
tikhub/api/v1/endpoints/bilibili/web/__init__.py
tikhub/api/v1/endpoints/bilibili/web/bilibili_web.py
tikhub/api/v1/endpoints/captcha/__init__.py
tikhub/api/v1/endpoints/captcha/captcha_solver.py
tikhub/api/v1/endpoints/douyin/__init__.py
tikhub/api/v1/endpoints/douyin/app/__init__.py
tikhub/api/v1/endpoints/douyin/app/douyin_app_v1.py
tikhub/api/v1/endpoints/douyin/app/douyin_app_v2.py
tikhub/api/v1/endpoints/douyin/app/douyin_app_v3.py
tikhub/api/v1/endpoints/douyin/web/__init__.py
tikhub/api/v1/endpoints/douyin/web/douyin_web.py
tikhub/api/v1/endpoints/hybrid_parsing/__init__.py
tikhub/api/v1/endpoints/hybrid_parsing/hybrid_parsing.py
tikhub/api/v1/endpoints/instagram/__init__.py
tikhub/api/v1/endpoints/instagram/web/__init__.py
tikhub/api/v1/endpoints/instagram/web/instagram_web.py
tikhub/api/v1/endpoints/kuaishou/__init__.py
tikhub/api/v1/endpoints/kuaishou/web/__init__.py
tikhub/api/v1/endpoints/kuaishou/web/kuaishou_web.py
tikhub/api/v1/endpoints/net_ease_cloud_music/__init__.py
tikhub/api/v1/endpoints/net_ease_cloud_music/app/__init__.py
tikhub/api/v1/endpoints/net_ease_cloud_music/app/net_ease_cloud_music_app_v1.py
tikhub/api/v1/endpoints/temp_mail/__init__.py
tikhub/api/v1/endpoints/temp_mail/temp_mail_v1.py
tikhub/api/v1/endpoints/tikhub/__init__.py
tikhub/api/v1/endpoints/tikhub/tikhub_user.py
tikhub/api/v1/endpoints/tiktok/__init__.py
tikhub/api/v1/endpoints/tiktok/app/__init__.py
tikhub/api/v1/endpoints/tiktok/app/tiktok_app_v2.py
tikhub/api/v1/endpoints/tiktok/app/tiktok_app_v3.py
tikhub/api/v1/endpoints/tiktok/web/__init__.py
tikhub/api/v1/endpoints/tiktok/web/tiktok_web.py
tikhub/api/v1/endpoints/twitter/__init__.py
tikhub/api/v1/endpoints/twitter/web/__init__.py
tikhub/api/v1/endpoints/twitter/web/twitter_web.py
tikhub/api/v1/endpoints/weibo/__init__.py
tikhub-1.13.0.dist-info/LICENSE
tikhub-1.13.0.dist-info/METADATA
tikhub-1.13.0.dist-info/WHEEL
tikhub-1.13.0.dist-info/top_level.txt
tikhub-1.13.0.dist-info/RECORD
