Metadata-Version: 2.1
Name: tikhub
Version: 1.13.0
Summary: A Python SDK for TikHub RESTful API
Home-page: https://github.com/TikHubIO/TikHub-API-Python-SDK
Author: TikHub.io
Author-email: tikhub.io@proton.me
Classifier: Programming Language :: Python :: 3
Classifier: License :: OSI Approved :: Apache Software License
Classifier: Operating System :: OS Independent
Requires-Python: >=3.6
License-File: LICENSE
Requires-Dist: httpx >=0.27.0
Requires-Dist: rich ~=13.7.1
Requires-Dist: websockets ~=12.0
